speculative_decoding/__init__.py
speculative_decoding/speculative_decoding.py
speculative_decoding/speculative_decoding_with_prophet.py
speculative_decoding-0.2.0.dist-info/LICENSE
speculative_decoding-0.2.0.dist-info/METADATA
speculative_decoding-0.2.0.dist-info/WHEEL
speculative_decoding-0.2.0.dist-info/top_level.txt
speculative_decoding-0.2.0.dist-info/RECORD
