Metadata-Version: 2.1
Name: speculative-decoding
Version: 0.2.0
Summary: Speculative Decoding
Home-page: https://github.com/lucidrains/speculative-decoding
Author: Phil Wang
Author-email: lucidrains@gmail.com
License: MIT
Keywords: artificial intelligence,deep learning,transformers,efficient decoding
Classifier: Development Status :: 4 - Beta
Classifier: Intended Audience :: Developers
Classifier: Topic :: Scientific/Engineering :: Artificial Intelligence
Classifier: License :: OSI Approved :: MIT License
Classifier: Programming Language :: Python :: 3.6
License-File: LICENSE
Requires-Dist: beartype
Requires-Dist: einops>=0.8.0
Requires-Dist: torch>=2.4
